dropboxignore/.dropboxignore
dropboxignore/__init__.py
dropboxignore/__main__.py
dropboxignore/cli.py
dropboxignore/paths_to_ignore.py
dropboxignore/shell.py
dot_dropbox_ignore-0.2.0.dist-info/LICENSE
dot_dropbox_ignore-0.2.0.dist-info/METADATA
dot_dropbox_ignore-0.2.0.dist-info/WHEEL
dot_dropbox_ignore-0.2.0.dist-info/entry_points.txt
dot_dropbox_ignore-0.2.0.dist-info/top_level.txt
dot_dropbox_ignore-0.2.0.dist-info/RECORD
